tidy_dir/__init__.py
tidy_dir/clean.py
tidy_dir/cli.py
tidy_dir/config.py
tidy_dir/tests/__init__.py
tidy_dir/tests/conftest.py
tidy_dir/tests/test_clean.py
tidy_dir/tests/test_config.py
tidy_dir-0.0.2.dist-info/LICENSE
tidy_dir-0.0.2.dist-info/METADATA
tidy_dir-0.0.2.dist-info/WHEEL
tidy_dir-0.0.2.dist-info/entry_points.txt
tidy_dir-0.0.2.dist-info/top_level.txt
tidy_dir-0.0.2.dist-info/RECORD
