Metadata-Version: 2.1
Name: tidy-dir
Version: 0.0.2
Summary: A package to tidy up directories using a configuration file
Home-page: https://github.com/mka142/tidy-dir
Author: mka142
Author-email: mka@diveinai.com
License-File: LICENSE
